LICENSE.txt
MANIFEST.in
README.rst
setup.cfg
setup.py
version.py
pynb/__init__.py
pynb/notebook.py
pynb/utils.py
pynb/version.py
pynb.egg-info/PKG-INFO
pynb.egg-info/SOURCES.txt
pynb.egg-info/dependency_links.txt
pynb.egg-info/entry_points.txt
pynb.egg-info/requires.txt
pynb.egg-info/top_level.txt