Metadata-Version: 1.2
Name: pynb
Version: 0.1.36
Summary: Manage Jupyter notebooks as Python code with embedded Markdown text.
Home-page: https://github.com/minodes/pynb
Author: Michele Dallachiesa
Author-email: michele.dallachiesa@minodes.com
License: MIT
Platform: UNKNOWN
Classifier: Development Status :: 3 - Alpha
Classifier: Intended Audience :: Developers
Classifier: Intended Audience :: Science/Research
Classifier: Intended Audience :: System Administrators
Classifier: License :: OSI Approved :: MIT License
Classifier: Programming Language :: Python :: 3
Requires-Python: >=3.4
